atlas_init/__init__.py
atlas_init/__main__.py
atlas_init/atlas_init.yaml
atlas_init/cli.py
atlas_init/cli_args.py
atlas_init/humps.py
atlas_init/terraform.yaml
atlas_init/typer_app.py
atlas_init/cli_cfn/__init__.py
atlas_init/cli_cfn/app.py
atlas_init/cli_cfn/aws.py
atlas_init/cli_cfn/cfn_parameter_finder.py
atlas_init/cli_cfn/contract.py
atlas_init/cli_cfn/example.py
atlas_init/cli_cfn/files.py
atlas_init/cli_helper/__init__.py
atlas_init/cli_helper/go.py
atlas_init/cli_helper/run.py
atlas_init/cli_helper/run_manager.py
atlas_init/cli_helper/sdk.py
atlas_init/cli_helper/sdk_auto_changes.py
atlas_init/cli_helper/tf_runner.py
atlas_init/cli_root/__init__.py
atlas_init/cli_root/aws_clean.py
atlas_init/cli_root/go_test.py
atlas_init/cli_root/mms_released.py
atlas_init/cli_root/trigger.py
atlas_init/cli_tf/__init__.py
atlas_init/cli_tf/app.py
atlas_init/cli_tf/changelog.py
atlas_init/cli_tf/ci_tests.py
atlas_init/cli_tf/debug_logs.py
atlas_init/cli_tf/debug_logs_test_data.py
atlas_init/cli_tf/debug_logs_test_data_package_config.py
atlas_init/cli_tf/example_update.py
atlas_init/cli_tf/github_logs.py
atlas_init/cli_tf/go_test_run.py
atlas_init/cli_tf/go_test_summary.py
atlas_init/cli_tf/go_test_tf_error.py
atlas_init/cli_tf/log_clean.py
atlas_init/cli_tf/mock_tf_log.py
atlas_init/cli_tf/openapi.py
atlas_init/cli_tf/schema.py
atlas_init/cli_tf/schema_go_parser.py
atlas_init/cli_tf/schema_inspection.py
atlas_init/cli_tf/schema_table.py
atlas_init/cli_tf/schema_table_models.py
atlas_init/cli_tf/schema_v2.py
atlas_init/cli_tf/schema_v2_sdk.py
atlas_init/cli_tf/schema_v3.py
atlas_init/cli_tf/schema_v3_sdk.py
atlas_init/cli_tf/schema_v3_sdk_base.py
atlas_init/cli_tf/schema_v3_sdk_create.py
atlas_init/cli_tf/codegen/__init__.py
atlas_init/cli_tf/codegen/models.py
atlas_init/cli_tf/codegen/openapi_minimal.py
atlas_init/cli_tf/hcl/__init__.py
atlas_init/cli_tf/hcl/cli.py
atlas_init/cli_tf/hcl/cluster_mig.py
atlas_init/cli_tf/hcl/modifier.py
atlas_init/cli_tf/hcl/modifier2.py
atlas_init-0.10.1.dist-info/METADATA
atlas_init-0.10.1.dist-info/WHEEL
atlas_init-0.10.1.dist-info/entry_points.txt
atlas_init-0.10.1.dist-info/licenses/LICENSE
atlas_init-0.10.1.dist-info/RECORD
