Metadata-Version: 2.4
Name: atlas-init
Version: 0.10.1
Project-URL: Documentation, https://github.com/EspenAlbert/atlas-init#readme
Project-URL: Issues, https://github.com/EspenAlbert/atlas-init/issues
Project-URL: Source, https://github.com/EspenAlbert/atlas-init
Author-email: EspenAlbert <albertespen@gmail.com>
License-Expression: MIT
License-File: LICENSE
Classifier: Development Status :: 4 - Beta
Classifier: Programming Language :: Python
Classifier: Programming Language :: Python :: 3.13
Requires-Python: >=3.13
Requires-Dist: appdirs==1.4.4
Requires-Dist: ask-shell>=0.0.5
Requires-Dist: boto3==1.35.92
Requires-Dist: gitpython==3.1.42
Requires-Dist: humanize==4.9.0
Requires-Dist: inflection==0.5.1
Requires-Dist: model-lib
Requires-Dist: motor==3.7.1
Requires-Dist: mypy-boto3-cloudformation==1.37.22
Requires-Dist: mypy-boto3-iam>=1.40.0
Requires-Dist: orjson==3.10.13
Requires-Dist: pydantic-settings==2.7.1
Requires-Dist: pydot==4.0.1
Requires-Dist: pygithub==2.6.1
Requires-Dist: python-hcl2==7.1.0
Requires-Dist: questionary==2.1.0
Requires-Dist: requests==2.32.2
Requires-Dist: rich==14.0.0
Requires-Dist: stringcase==1.2.0
Requires-Dist: tenacity==9.0.0
Requires-Dist: typer>=0.15.1
Requires-Dist: zero-3rdparty==1.0.0b5
